MANIFEST.in
setup.py
etc/colab/plugins.d/audiencias.py
etc/colab/widgets.d/audiencias_widgets.py
src/colab_audiencias/__init__.py
src/colab_audiencias/apps.py
src/colab_audiencias/data_importer.py
src/colab_audiencias/diazo.xml
src/colab_audiencias/models.py
src/colab_audiencias/search_indexes.py
src/colab_audiencias/tasks.py
src/colab_audiencias/urls.py
src/colab_audiencias/views.py
src/colab_audiencias.egg-info/PKG-INFO
src/colab_audiencias.egg-info/SOURCES.txt
src/colab_audiencias.egg-info/dependency_links.txt
src/colab_audiencias.egg-info/not-zip-safe
src/colab_audiencias.egg-info/requires.txt
src/colab_audiencias.egg-info/top_level.txt
src/colab_audiencias/management/__init__.py
src/colab_audiencias/management/commands/__init__.py
src/colab_audiencias/management/commands/fetch_data_audiencias.py
src/colab_audiencias/migrations/0001_initial.py
src/colab_audiencias/migrations/0002_auto_20170323_1427.py
src/colab_audiencias/migrations/0003_audienciasroom_is_visible.py
src/colab_audiencias/migrations/0004_auto_20170403_2118.py
src/colab_audiencias/migrations/0005_auto_20170420_2029.py
src/colab_audiencias/migrations/0006_auto_20170524_1404.py
src/colab_audiencias/migrations/0007_auto_20171101_1720.py
src/colab_audiencias/migrations/__init__.py
src/colab_audiencias/templates/proxy/audiencias.html
src/colab_audiencias/templates/search/indexes/room_search_preview.html
src/colab_audiencias/templates/search/indexes/colab_audiencias/audienciasroom_text.txt
src/colab_audiencias/templates/widgets/audiencias_home_section.html
src/colab_audiencias/templates/widgets/audiencias_navigation_link.html
src/colab_audiencias/widgets/__init__.py
src/colab_audiencias/widgets/home_section.py
src/colab_audiencias/widgets/navigation_links.py