Metadata-Version: 1.1
Name: colab-audiencias
Version: 0.2.2
Summary: Colab Audiencias Plugin
Home-page: https://github.com/labhackercd/colab-audiencias-plugin
Author: labhackercd
Author-email: labhackercd@gmail.com
License: GPLv3
Platform: UNKNOWN
Classifier: Framework :: Django
Classifier: Intended Audience :: Developers
Classifier: Intended Audience :: System Administrators
Classifier: Operating System :: OS Independent
Classifier: Topic :: Software Development
